anontex/__init__.py
anontex/anontex_cli.py
anontex/constants.py
anontex/engines.py
anontex/exceptions.py
anontex/languages-config-transformer.yml
anontex/languages-config.yml
anontex/routes/__init__.py
anontex/routes/openai_proxy.py
anontex/tests/__init__.py
anontex/tests/test_engines/__init__.py
anontex/tests/test_engines/test_anonymizer.py
anontex/tests/test_engines/test_deanonymizer.py
anontex/tests/test_engines/test_normalizer.py
anontex-0.2.6.dist-info/LICENSE
anontex-0.2.6.dist-info/METADATA
anontex-0.2.6.dist-info/WHEEL
anontex-0.2.6.dist-info/entry_points.txt
anontex-0.2.6.dist-info/RECORD
