Metadata-Version: 2.3
Name: anontex
Version: 0.2.6
Summary: PII anonymizer as a LLM proxy
License: Apache License
Keywords: PII,LLM,Proxy
Author: Chamath Attanyaka
Author-email: kaushalyabandaraatta@gmail.com
Requires-Python: >=3.11
Classifier: License :: OSI Approved :: Apache Software License
Classifier: Programming Language :: Python
Classifier: Programming Language :: Python :: 3
Provides-Extra: dev
Provides-Extra: transformers
Requires-Dist: aiohttp (>=3.11.13,<4.0.0)
Requires-Dist: black ; extra == "dev"
Requires-Dist: click (>=8.1.8,<9.0.0)
Requires-Dist: faker (>=36.1.1,<37.0.0)
Requires-Dist: fastapi (>=0.115.8,<0.116.0)
Requires-Dist: flake8 ; extra == "dev"
Requires-Dist: isort ; extra == "dev"
Requires-Dist: mypy ; extra == "dev"
Requires-Dist: presidio-analyzer (==2.2.355)
Requires-Dist: presidio_analyzer[transformers] (==2.2.355) ; extra == "transformers"
Requires-Dist: pydantic (>=2.10.6,<3.0.0)
Requires-Dist: pytest (>=8.3.5,<9.0.0)
Requires-Dist: redis (>=5.2.1,<6.0.0)
Requires-Dist: uvicorn (>=0.34.0,<0.35.0)
Project-URL: Repository, https://github.com/ChamathKB/AnonTex
